baseqDrops/__init__.py
baseqDrops/aggregate.py
baseqDrops/cmd.py
baseqDrops/command.py
baseqDrops/config.py
baseqDrops/error.py
baseqDrops/file_reader.py
baseqDrops/pipeline.py
baseqDrops/sampling.py
baseqDrops/star.py
baseqDrops/barcode/__init__.py
baseqDrops/barcode/correct.py
baseqDrops/barcode/count.py
baseqDrops/barcode/extract.py
baseqDrops/barcode/split.py
baseqDrops/barcode/split_fast.py
baseqDrops/barcode/stats.py
baseqDrops/barcode/whitelist.py
baseqDrops/stats/__init__.py
baseqDrops/stats/exp_stats.py
baseqDrops/tagging/__init__.py
baseqDrops/tagging/bam_parser.py
baseqDrops/tagging/prime3.py
baseqDrops/tagging/prime5.py
baseqDrops/tagging/refs.py
baseqDrops-2.0.dist-info/DESCRIPTION.rst
baseqDrops-2.0.dist-info/METADATA
baseqDrops-2.0.dist-info/RECORD
baseqDrops-2.0.dist-info/WHEEL
baseqDrops-2.0.dist-info/entry_points.txt
baseqDrops-2.0.dist-info/metadata.json
baseqDrops-2.0.dist-info/top_level.txt
