Metadata-Version: 2.0
Name: baseqDrops
Version: 2.0
Summary: Processing Drop-seq, 10X(3prime) and inDrop RNA-seq dataset
Home-page: https://gene.pku.edu.cn
Author: Xiannian Zhang
Author-email: friedpine@gmail.com
License: UNKNOWN
Keywords: sample setuptools development
Platform: UNKNOWN
Classifier: Development Status :: 3 - Alpha
Classifier: Intended Audience :: Developers
Classifier: Topic :: Software Development :: Build Tools
Classifier: License :: OSI Approved :: MIT License
Classifier: Programming Language :: Python :: 3.6
Requires-Dist: click
Requires-Dist: configparser
Requires-Dist: matplotlib
Requires-Dist: numpy
Requires-Dist: pandas
Requires-Dist: pysam
Provides-Extra: dev
Requires-Dist: check-manifest; extra == 'dev'
Provides-Extra: test
Requires-Dist: coverage; extra == 'test'
